[
  {
    "name": "Автово"
  },
  {
    "name": "Адмиралтейская"
  },
  {
    "name": "Академическая"
  },
  {
    "name": "Балтийская"
  },
  {
    "name": "Бухарестская"
  },
  {
    "name": "Василеостровская"
  },
  {
    "name": "Владимирская"
  },
  {
    "name": "Волковская"
  },
  {
    "name": "Выборгская"
  },
  {
    "name": "Горьковская"
  },
  {
    "name": "Гостиный двор"
  },
  {
    "name": "Гражданский проспект"
  },
  {
    "name": "Девяткино"
  },
  {
    "name": "Достоевская"
  },
  {
    "name": "Елизаровская"
  },
  {
    "name": "Звёздная"
  },
  {
    "name": "Звенигородская"
  },
  {
    "name": "Кировский завод"
  },
  {
    "name": "Комендантский проспект"
  },
  {
    "name": "Крестовский остров"
  },
  {
    "name": "Купчино"
  },
  {
    "name": "Ладожская"
  },
  {
    "name": "Ленинский проспект"
  },
  {
    "name": "Лесная"
  },
  {
    "name": "Лиговский проспект"
  },
  {
    "name": "Ломоносовская"
  },
  {
    "name": "Маяковская"
  },
  {
    "name": "Международная"
  },
  {
    "name": "Московская"
  },
  {
    "name": "Московские ворота"
  },
  {
    "name": "Нарвская"
  },
  {
    "name": "Невский проспект"
  },
  {
    "name": "Новочеркасская"
  },
  {
    "name": "Обводный канал"
  },
  {
    "name": "Обухово"
  },
  {
    "name": "Озерки"
  },
  {
    "name": "Парк Победы"
  },
  {
    "name": "Парнас"
  },
  {
    "name": "Петроградская"
  },
  {
    "name": "Пионерская"
  },
  {
    "name": "Площадь Александра Невского I"
  },
  {
    "name": "Площадь Восстания"
  },
  {
    "name": "Площадь Ленина"
  },
  {
    "name": "Площадь Мужества"
  },
  {
    "name": "Площадь Невского"
  },
  {
    "name": "Политехническая"
  },
  {
    "name": "Приморская"
  },
  {
    "name": "Пролетарская"
  },
  {
    "name": "Проспект Большевиков"
  },
  {
    "name": "Проспект Ветеранов"
  },
  {
    "name": "Проспект Просвещения"
  },
  {
    "name": "Пушкинская"
  },
  {
    "name": "Рыбацкое"
  },
  {
    "name": "Садовая"
  },
  {
    "name": "Сенная площадь"
  },
  {
    "name": "Спасская"
  },
  {
    "name": "Спортивная"
  },
  {
    "name": "Старая Деревня"
  },
  {
    "name": "Технологический институт I"
  },
  {
    "name": "Технологический институт II"
  },
  {
    "name": "Удельная"
  },
  {
    "name": "Улица Дыбенко"
  },
  {
    "name": "Фрунзенская"
  },
  {
    "name": "Чёрная речка"
  },
  {
    "name": "Чернышевская"
  },
  {
    "name": "Чкаловская"
  },
  {
    "name": "Электросила"
  }
]
